[{"name":"Rugil\u0117","surname":"Garliauskien\u0117","id":"3456","acc":"LT012345699989977422","funds":900},{"name":"Rugil\u0117","surname":"Garliauskien\u0117","id":"3456s","acc":"LT012345633038505326","funds":0},{"name":"vasa","surname":"masia","id":"50107288468","acc":"LT012345631819415852","funds":0},{"name":"dzfc","surname":"dzc","id":"47604029588","acc":"LT012345614929767016","funds":0},{"name":"Mantasas","surname":"Karabasas","id":"31604218822","acc":"LT012345698854926887","funds":0},{"name":"KArabasanasa","surname":"BAnasasa","id":"36708159514","acc":"LT012345633091749865","funds":0},{"name":"Benajminas","surname":"Kakauskas","id":"44502279172","acc":"LT012345695518182513","funds":0}]